cucu/__init__.py
cucu/ansi_parser.py
cucu/behave_tweaks.py
cucu/browser/__init__.py
cucu/browser/core.py
cucu/browser/frames.py
cucu/browser/selenium.py
cucu/browser/selenium_tweaks.py
cucu/cli/__init__.py
cucu/cli/core.py
cucu/cli/run.py
cucu/cli/steps.py
cucu/cli/thread_dumper.py
cucu/config.py
cucu/db.py
cucu/edgedriver_autoinstaller/README.md
cucu/edgedriver_autoinstaller/__init__.py
cucu/edgedriver_autoinstaller/utils.py
cucu/environment.py
cucu/external/jquery/jquery-3.5.1.min.js
cucu/formatter/__init__.py
cucu/formatter/cucu.py
cucu/formatter/json.py
cucu/formatter/junit.py
cucu/formatter/rundb.py
cucu/fuzzy/__init__.py
cucu/fuzzy/core.py
cucu/fuzzy/fuzzy.js
cucu/helpers.py
cucu/hooks.py
cucu/init_data/.gitignore
cucu/init_data/README.md
cucu/init_data/cucurc.yml
cucu/init_data/data/www/example.html
cucu/init_data/features/cucurc.yml
cucu/init_data/features/environment.py
cucu/init_data/features/example.feature
cucu/init_data/features/lint_rules/sid.yaml
cucu/init_data/features/steps/__init__.py
cucu/init_data/features/steps/my_steps.py
cucu/language_server/__init__.py
cucu/language_server/core.py
cucu/lint/__init__.py
cucu/lint/linter.py
cucu/lint/rules/format.yaml
cucu/logger.py
cucu/matcher/__init__.py
cucu/matcher/core.py
cucu/page_checks.py
cucu/reporter/__init__.py
cucu/reporter/external/bootstrap.min.css
cucu/reporter/external/bootstrap.min.js
cucu/reporter/external/dataTables.bootstrap.min.css
cucu/reporter/external/dataTables.bootstrap.min.js
cucu/reporter/external/jquery-3.5.1.min.js
cucu/reporter/external/jquery.dataTables.min.js
cucu/reporter/external/manage_scenario_highlights.js
cucu/reporter/external/popper.min.js
cucu/reporter/favicon.png
cucu/reporter/html.py
cucu/reporter/templates/feature.html
cucu/reporter/templates/flat.html
cucu/reporter/templates/index.html
cucu/reporter/templates/layout.html
cucu/reporter/templates/scenario.html
cucu/steps/__init__.py
cucu/steps/base_steps.py
cucu/steps/browser_steps.py
cucu/steps/button_steps.py
cucu-1.4.4.dist-info/licenses/LICENSE
cucu-1.4.4.dist-info/WHEEL
cucu-1.4.4.dist-info/entry_points.txt
cucu-1.4.4.dist-info/METADATA
cucu-1.4.4.dist-info/RECORD
