Metadata-Version: 2.4
Name: cucu
Version: 1.4.4
Summary: Easy BDD web testing
Keywords: cucumber,selenium,behave
Author: Domino Data Lab, Rodney Gomes, Cedric Young, Xin Dong, Kavya Yakkati, Kevin Garton, Joy Liao
Author-email: Domino Data Lab <open-source@dominodatalab.com>, Rodney Gomes <107359+rlgomes@users.noreply.github.com>, Cedric Young <4129217+ccedricyoung@users.noreply.github.com>, Xin Dong <104880864+ddl-xin@users.noreply.github.com>, Kavya Yakkati <91882851+ddl-kavya@users.noreply.github.com>, Kevin Garton <71028750+ddl-kgarton@users.noreply.github.com>, Joy Liao <107583686+ddl-joy-liao@users.noreply.github.com>
License-Expression: BSD-3-Clause-Clear
License-File: LICENSE
Classifier: Development Status :: 4 - Beta
Classifier: Environment :: Console
Classifier: Intended Audience :: Developers
Classifier: License :: OSI Approved :: BSD License
Classifier: Operating System :: OS Independent
Classifier: Natural Language :: English
Classifier: Topic :: Software Development :: Testing :: BDD
Requires-Dist: beautifulsoup4~=4.14.2
Requires-Dist: behave==1.2.6
Requires-Dist: chromedriver-autoinstaller~=0.6.2
Requires-Dist: click~=8.3.0
Requires-Dist: coverage[toml]~=7.8
Requires-Dist: geckodriver-autoinstaller~=0.1.0
Requires-Dist: humanize~=4.15.0
Requires-Dist: importlib-metadata~=8.7.0
Requires-Dist: jellyfish>=1.1
Requires-Dist: jinja2~=3.1.3
Requires-Dist: lsprotocol>=2025.0.0
Requires-Dist: mpire~=2.10.2
Requires-Dist: peewee>=3.18.2
Requires-Dist: psutil>=6.0
Requires-Dist: pygls>=2.0.0
Requires-Dist: pyyaml~=6.0.1
Requires-Dist: requests>=2.31.0,<3.0.0
Requires-Dist: selenium>=4.38
Requires-Dist: tabulate~=0.9.0
Requires-Dist: tenacity>=9.0
Maintainer: Domino Data Lab, Cedric Young, Kevin Garton, Brian Colby
Maintainer-email: Domino Data Lab <open-source@dominodatalab.com>, Cedric Young <4129217+ccedricyoung@users.noreply.github.com>, Kevin Garton <71028750+ddl-kgarton@users.noreply.github.com>, Brian Colby <92048365+ddl-bcolby@users.noreply.github.com>
Requires-Python: >=3.10
Project-URL: Homepage, https://github.com/dominodatalab/cucu/wiki
Project-URL: Download, https://pypi.org/project/cucu/
Project-URL: Source Code, https://github.com/dominodatalab/cucu
